open_qr_plus/__init__.py
open_qr_plus/server.py
open_qr_plus/templates/index.html
open_qr_plus-1.4.0.dist-info/METADATA
open_qr_plus-1.4.0.dist-info/WHEEL
open_qr_plus-1.4.0.dist-info/entry_points.txt
open_qr_plus-1.4.0.dist-info/top_level.txt
open_qr_plus-1.4.0.dist-info/RECORD
