Metadata-Version: 2.1
Name: open_qr_plus
Version: 1.4.0
Summary: A perfect solution for qr generation with stunning ui...
Author: Sandesh Kumar
Author-email: connect@sandeshai.in
Classifier: Programming Language :: Python :: 3
Classifier: Operating System :: OS Independent
Requires-Python: >=3.10
Requires-Dist: Flask==3.0.3
Requires-Dist: qrcode[pil]==8.0
Requires-Dist: Flask-WTF==1.2.2
Requires-Dist: cryptography==43.0.3
Requires-Dist: Werkzeug==3.1.2
Requires-Dist: Pillow==11.0.0
Requires-Dist: colorama==0.4.6
Requires-Dist: pyfiglet==1.0.2
Requires-Dist: pyzbar==0.1.9
